{
  "realms": [
    "master",
    "test-realm",
    "production",
    "dev-realm",
    "staging",
    "demo",
    "customer-realm",
    "partner-realm",
    "internal",
    "external",
    "app-realm",
    "service-realm",
    "oauth-realm",
    "saml-realm",
    "oidc-realm",
    "test",
    "prod",
    "develop",
    "qa-realm",
    "uat-realm"
  ],
  "client_ids": [
    "account",
    "admin-cli",
    "broker",
    "realm-management",
    "security-admin-console",
    "my-app",
    "web-app",
    "mobile-app",
    "api-client",
    "service-account",
    "public-client",
    "confidential-client",
    "bearer-only-client",
    "spa-client",
    "backend-service",
    "frontend-app",
    "oauth2-client",
    "oidc-client",
    "saml-client",
    "test-client"
  ],
  "usernames": [
    "admin",
    "user",
    "testuser",
    "john.doe",
    "jane.smith",
    "alice",
    "bob",
    "charlie",
    "david",
    "emily",
    "service-account",
    "api-user",
    "system-user",
    "test@example.com",
    "admin@test.com",
    "user@demo.com",
    "john@keycloak.org",
    "jane@company.com",
    "alice123",
    "bob.jones"
  ],
  "user_ids": [
    "f8c3de3d-1fea-4d7c-a8b0-29f63c4c3454",
    "a1b2c3d4-e5f6-4a5b-8c9d-0e1f2a3b4c5d",
    "12345678-1234-1234-1234-123456789012",
    "abcdef01-2345-6789-abcd-ef0123456789",
    "00000000-0000-0000-0000-000000000001",
    "11111111-1111-1111-1111-111111111111",
    "22222222-2222-2222-2222-222222222222",
    "99999999-9999-9999-9999-999999999999",
    "aaaaaaaa-aaaa-aaaa-aaaa-aaaaaaaaaaaa",
    "bbbbbbbb-bbbb-bbbb-bbbb-bbbbbbbbbbbb"
  ],
  "roles": [
    "admin",
    "user",
    "view-profile",
    "manage-account",
    "manage-users",
    "view-users",
    "manage-clients",
    "view-clients",
    "manage-realm",
    "view-realm",
    "manage-identity-providers",
    "view-identity-providers",
    "view-events",
    "manage-authorization",
    "query-users",
    "query-groups",
    "view-authorization",
    "impersonation",
    "create-client",
    "offline_access"
  ],
  "groups": [
    "admin-group",
    "users-group",
    "developers",
    "managers",
    "operators",
    "customers",
    "partners",
    "internal-users",
    "external-users",
    "test-group",
    "engineering",
    "sales",
    "support",
    "finance",
    "hr-department",
    "it-team",
    "qa-team",
    "devops",
    "security-team",
    "executives"
  ],
  "scopes": [
    "openid",
    "profile",
    "email",
    "address",
    "phone",
    "offline_access",
    "roles",
    "web-origins",
    "microprofile-jwt",
    "acr",
    "read",
    "write",
    "admin",
    "user",
    "api",
    "full_access",
    "read:users",
    "write:users",
    "delete:users",
    "manage:realm"
  ],
  "grant_types": [
    "authorization_code",
    "implicit",
    "password",
    "client_credentials",
    "refresh_token",
    "urn:ietf:params:oauth:grant-type:device_code",
    "urn:openid:params:grant-type:ciba",
    "urn:ietf:params:oauth:grant-type:token-exchange"
  ],
  "response_types": [
    "code",
    "token",
    "id_token",
    "code token",
    "code id_token",
    "token id_token",
    "code token id_token",
    "none"
  ],
  "protocol_mappers": [
    "oidc-usermodel-property-mapper",
    "oidc-usermodel-attribute-mapper",
    "oidc-role-name-mapper",
    "oidc-full-name-mapper",
    "oidc-address-mapper",
    "oidc-audience-mapper",
    "oidc-hardcoded-claim-mapper",
    "oidc-group-membership-mapper",
    "saml-user-property-mapper",
    "saml-user-attribute-mapper",
    "saml-role-list-mapper",
    "saml-hardcoded-attribute-mapper"
  ],
  "identity_providers": [
    "oidc",
    "saml",
    "keycloak-oidc",
    "google",
    "facebook",
    "github",
    "microsoft",
    "linkedin",
    "twitter",
    "instagram",
    "gitlab",
    "bitbucket",
    "stackoverflow",
    "openshift-v3",
    "openshift-v4"
  ],
  "authentication_flows": [
    "browser",
    "direct grant",
    "registration",
    "reset credentials",
    "client authentication",
    "docker auth",
    "http challenge",
    "first broker login",
    "saml ecp"
  ],
  "required_actions": [
    "CONFIGURE_TOTP",
    "UPDATE_PASSWORD",
    "UPDATE_PROFILE",
    "VERIFY_EMAIL",
    "terms_and_conditions",
    "update_user_locale",
    "webauthn-register",
    "webauthn-register-passwordless",
    "delete_account"
  ],
  "event_types": [
    "LOGIN",
    "LOGIN_ERROR",
    "LOGOUT",
    "REGISTER",
    "REGISTER_ERROR",
    "UPDATE_PASSWORD",
    "UPDATE_PROFILE",
    "VERIFY_EMAIL",
    "REMOVE_TOTP",
    "UPDATE_TOTP",
    "CODE_TO_TOKEN",
    "CODE_TO_TOKEN_ERROR",
    "CLIENT_LOGIN",
    "CLIENT_LOGIN_ERROR",
    "REFRESH_TOKEN",
    "REFRESH_TOKEN_ERROR",
    "FEDERATED_IDENTITY_LINK",
    "REMOVE_FEDERATED_IDENTITY",
    "SEND_VERIFY_EMAIL",
    "SEND_RESET_PASSWORD"
  ],
  "admin_event_operations": [
    "CREATE",
    "UPDATE",
    "DELETE",
    "ACTION"
  ],
  "resource_types": [
    "REALM",
    "REALM_ROLE",
    "REALM_ROLE_MAPPING",
    "REALM_SCOPE_MAPPING",
    "AUTH_FLOW",
    "AUTH_EXECUTION_FLOW",
    "AUTH_EXECUTION",
    "AUTHENTICATOR_CONFIG",
    "REQUIRED_ACTION",
    "IDENTITY_PROVIDER",
    "IDENTITY_PROVIDER_MAPPER",
    "PROTOCOL_MAPPER",
    "USER",
    "USER_LOGIN_FAILURE",
    "USER_SESSION",
    "USER_FEDERATION_PROVIDER",
    "USER_FEDERATION_MAPPER",
    "GROUP",
    "GROUP_MEMBERSHIP",
    "CLIENT",
    "CLIENT_INITIAL_ACCESS",
    "CLIENT_ROLE",
    "CLIENT_ROLE_MAPPING",
    "CLIENT_SCOPE",
    "CLIENT_SCOPE_CLIENT_MAPPING",
    "CLUSTER_NODE",
    "COMPONENT",
    "AUTHORIZATION_RESOURCE_SERVER",
    "AUTHORIZATION_RESOURCE",
    "AUTHORIZATION_SCOPE",
    "AUTHORIZATION_POLICY",
    "CUSTOM"
  ],
  "policy_logic": [
    "POSITIVE",
    "NEGATIVE"
  ],
  "decision_strategy": [
    "AFFIRMATIVE",
    "UNANIMOUS",
    "CONSENSUS"
  ],
  "policy_types": [
    "role",
    "group",
    "user",
    "client",
    "time",
    "js",
    "aggregate",
    "scope"
  ],
  "token_types": [
    "Bearer",
    "Refresh",
    "ID",
    "Offline",
    "AccessToken",
    "RefreshToken",
    "IDToken"
  ],
  "algorithms": [
    "RS256",
    "RS384",
    "RS512",
    "HS256",
    "HS384",
    "HS512",
    "ES256",
    "ES384",
    "ES512",
    "PS256",
    "PS384",
    "PS512"
  ],
  "signature_algorithms": [
    "RSA_USING_SHA256",
    "RSA_USING_SHA384",
    "RSA_USING_SHA512",
    "DSA_USING_SHA256",
    "ECDSA_USING_SHA256",
    "ECDSA_USING_SHA384",
    "ECDSA_USING_SHA512",
    "HMAC_USING_SHA256",
    "HMAC_USING_SHA384",
    "HMAC_USING_SHA512"
  ],
  "credential_types": [
    "password",
    "otp",
    "webauthn",
    "webauthn-passwordless",
    "kerberos",
    "secret"
  ],
  "user_storage_providers": [
    "ldap",
    "kerberos",
    "ad",
    "readonly-ldap"
  ],
  "ldap_vendor": [
    "ad",
    "rhds",
    "tivoli",
    "eDirectory",
    "other"
  ],
  "edit_mode": [
    "READ_ONLY",
    "WRITABLE",
    "UNSYNCED"
  ],
  "session_state": [
    "LOGGED_IN",
    "LOGGED_OUT",
    "LOGGING_OUT"
  ],
  "client_session_state": [
    "ACTIVE",
    "EXPIRED"
  ],
  "execution_status": [
    "SUCCESS",
    "FAILED",
    "SETUP_REQUIRED",
    "ATTEMPTED",
    "SKIPPED",
    "CHALLENGED"
  ],
  "boolean_values": [
    "true",
    "false"
  ],
  "integers": [
    "0",
    "1",
    "5",
    "10",
    "30",
    "60",
    "100",
    "300",
    "600",
    "900",
    "1800",
    "3600",
    "86400",
    "-1",
    "999999"
  ],
  "locale": [
    "en",
    "de",
    "it",
    "fr",
    "es",
    "pt-BR",
    "ja",
    "zh-CN",
    "ru",
    "cs",
    "pl",
    "nl",
    "sv"
  ]
}
